{
    "lyrics": [
        {
            "lyric": "♪",
            "showAt": 0.0,
            "hideAt": 4.382534027099609
        },
        {
            "lyric": "I threw a wish in the well\r",
            "showAt": 4.382534027099609,
            "hideAt": 6.365889549255371
        },
        {
            "lyric": "Don't ask me, I'll never tell\r",
            "showAt": 6.365889549255371,
            "hideAt": 8.349257469177246
        },
        {
            "lyric": "I looked to you as it fell\r",
            "showAt": 8.349257469177246,
            "hideAt": 10.432563781738282
        },
        {
            "lyric": "And now you're in my way\r",
            "showAt": 10.432563781738282,
            "hideAt": 12.465985298156739
        },
        {
            "lyric": "I trade my soul for a wish\r",
            "showAt": 12.465985298156739,
            "hideAt": 14.415959358215332
        },
        {
            "lyric": "Pennies and dimes for a kiss\r",
            "showAt": 14.415959358215332,
            "hideAt": 16.44928550720215
        },
        {
            "lyric": "I wasn't looking for this\r",
            "showAt": 16.44928550720215,
            "hideAt": 18.182607650756837
        },
        {
            "lyric": "But now you're in my way\r",
            "showAt": 18.182607650756837,
            "hideAt": 20.51583480834961
        },
        {
            "lyric": "Your stare was holdin'\r",
            "showAt": 20.51583480834961,
            "hideAt": 22.08251953125
        },
        {
            "lyric": "Ripped jeans, skin was showin'\r",
            "showAt": 22.08251953125,
            "hideAt": 24.115821838378908
        },
        {
            "lyric": "Hot night, wind was blowin'\r",
            "showAt": 24.115821838378908,
            "hideAt": 26.115734100341798
        },
        {
            "lyric": "Where you think you're going, baby?\r",
            "showAt": 26.115734100341798,
            "hideAt": 28.615671157836915
        },
        {
            "lyric": "Hey, I just met you, and this is crazy\r",
            "showAt": 28.615671157836915,
            "hideAt": 32.91585159301758
        },
        {
            "lyric": "But here's my number, so call me, maybe\r",
            "showAt": 32.91585159301758,
            "hideAt": 36.6657829284668
        },
        {
            "lyric": "It's hard to look right at you, baby\r",
            "showAt": 36.6657829284668,
            "hideAt": 40.91596603393555
        },
        {
            "lyric": "But here's my number, so call me, maybe\r",
            "showAt": 40.91596603393555,
            "hideAt": 44.64954376220703
        },
        {
            "lyric": "Hey, I just met you, and this is crazy\r",
            "showAt": 44.64954376220703,
            "hideAt": 48.96635818481445
        },
        {
            "lyric": "But here's my number, so call me, maybe\r",
            "showAt": 48.96635818481445,
            "hideAt": 52.46662139892578
        },
        {
            "lyric": "And all the other boys try to chase me\r",
            "showAt": 52.46662139892578,
            "hideAt": 56.949981689453128
        },
        {
            "lyric": "But here's my number, so call me, maybe\r",
            "showAt": 56.949981689453128,
            "hideAt": 64.46701049804688
        },
        {
            "lyric": "You took your time with the call\r",
            "showAt": 64.46701049804688,
            "hideAt": 66.33348846435547
        },
        {
            "lyric": "I took no time with the fall\r",
            "showAt": 66.33348846435547,
            "hideAt": 68.33360290527344
        },
        {
            "lyric": "You gave me nothing at all\r",
            "showAt": 68.33360290527344,
            "hideAt": 70.2999038696289
        },
        {
            "lyric": "But still, you're in my way\r",
            "showAt": 70.2999038696289,
            "hideAt": 72.48306274414063
        },
        {
            "lyric": "I beg and borrow and steal\r",
            "showAt": 72.48306274414063,
            "hideAt": 74.33284759521485
        },
        {
            "lyric": "At first sight, and it's real\r",
            "showAt": 74.33284759521485,
            "hideAt": 76.31604766845703
        },
        {
            "lyric": "I didn't know I would feel it\r",
            "showAt": 76.31604766845703,
            "hideAt": 78.58251190185547
        },
        {
            "lyric": "But it's in my way\r",
            "showAt": 78.58251190185547,
            "hideAt": 80.44904327392578
        },
        {
            "lyric": "Your stare was holdin'\r",
            "showAt": 80.44904327392578,
            "hideAt": 82.24886322021485
        },
        {
            "lyric": "Ripped jeans, skin was showin'\r",
            "showAt": 82.24886322021485,
            "hideAt": 84.24867248535156
        },
        {
            "lyric": "Hot night, wind was blowin'\r",
            "showAt": 84.24867248535156,
            "hideAt": 86.28185272216797
        },
        {
            "lyric": "Where you think you're going, baby?\r",
            "showAt": 86.28185272216797,
            "hideAt": 88.7149429321289
        },
        {
            "lyric": "Hey, I just met you, and this is crazy\r",
            "showAt": 88.7149429321289,
            "hideAt": 92.9478530883789
        },
        {
            "lyric": "But here's my number, so call me, maybe\r",
            "showAt": 92.9478530883789,
            "hideAt": 96.41436004638672
        },
        {
            "lyric": "It's hard to look right at you, baby\r",
            "showAt": 96.41436004638672,
            "hideAt": 100.86405944824219
        },
        {
            "lyric": "But here's my number, so call me, maybe\r",
            "showAt": 100.86405944824219,
            "hideAt": 104.5804672241211
        },
        {
            "lyric": "Hey, I just met you, and this is crazy\r",
            "showAt": 104.5804672241211,
            "hideAt": 108.86341857910156
        },
        {
            "lyric": "But here's my number, so call me, maybe\r",
            "showAt": 108.86341857910156,
            "hideAt": 112.47978210449219
        },
        {
            "lyric": "And all the other boys try to chase me\r",
            "showAt": 112.47978210449219,
            "hideAt": 116.87950897216797
        },
        {
            "lyric": "But here's my number, so call me, maybe\r",
            "showAt": 116.87950897216797,
            "hideAt": 120.77926635742188
        },
        {
            "lyric": "Before you came into my life, I missed you so bad\r",
            "showAt": 120.77926635742188,
            "hideAt": 124.36214447021485
        },
        {
            "lyric": "I missed you so bad, I missed you so, so bad\r",
            "showAt": 124.36214447021485,
            "hideAt": 128.42845153808595
        },
        {
            "lyric": "Before you came into my life, I missed you so bad\r",
            "showAt": 128.42845153808595,
            "hideAt": 132.2281036376953
        },
        {
            "lyric": "And you should know that\r",
            "showAt": 132.2281036376953,
            "hideAt": 134.52809143066407
        },
        {
            "lyric": "I missed you so, so bad\r",
            "showAt": 134.52809143066407,
            "hideAt": 136.79446411132813
        },
        {
            "lyric": "(Bad, bad, bad, bad, bad, bad)\r",
            "showAt": 136.79446411132813,
            "hideAt": 141.66079711914063
        },
        {
            "lyric": "",
            "showAt": 141.66079711914063,
            "hideAt": 144.5606231689453
        },
        {
            "lyric": "It's hard to look right at you, baby\r",
            "showAt": 144.5606231689453,
            "hideAt": 148.9768524169922
        },
        {
            "lyric": "But here's my number, so call me, maybe\r",
            "showAt": 148.9768524169922,
            "hideAt": 152.55992126464845
        },
        {
            "lyric": "Hey, I just met you, and this is crazy\r",
            "showAt": 152.55992126464845,
            "hideAt": 156.80955505371095
        },
        {
            "lyric": "But here's my number, so call me, maybe\r",
            "showAt": 156.80955505371095,
            "hideAt": 160.57583618164063
        },
        {
            "lyric": "And all the other boys try to chase me\r",
            "showAt": 160.57583618164063,
            "hideAt": 164.7923583984375
        },
        {
            "lyric": "But here's my number, so call me, maybe\r",
            "showAt": 164.7923583984375,
            "hideAt": 168.458740234375
        },
        {
            "lyric": "Before you came into my life, I missed you so bad\r",
            "showAt": 168.458740234375,
            "hideAt": 172.32496643066407
        },
        {
            "lyric": "I missed you so bad, I missed you so, so bad\r",
            "showAt": 172.32496643066407,
            "hideAt": 176.4247283935547
        },
        {
            "lyric": "Before you came into my life, I missed you so bad\r",
            "showAt": 176.4247283935547,
            "hideAt": 180.4244384765625
        },
        {
            "lyric": "And you should know that\r",
            "showAt": 180.4244384765625,
            "hideAt": 182.44088745117188
        },
        {
            "lyric": "So call me maybe",
            "showAt": 182.44088745117188,
            "hideAt": 184.22410583496095
        },
        {
            "lyric": "♪",
            "showAt": 184.22410583496095,
            "hideAt": 189.22410583496095
        }
    ]
}