{
    "lyrics": [
        {
            "lyric": "♪",
            "showAt": 0.0,
            "hideAt": 38.75246047973633
        },
        {
            "lyric": "They told him, \"Don't you ever come around here\"\r",
            "showAt": 38.75246047973633,
            "hideAt": 41.84975814819336
        },
        {
            "lyric": "\"Don't wanna see your face, you better disappear\"\r",
            "showAt": 41.84975814819336,
            "hideAt": 45.28300857543945
        },
        {
            "lyric": "The fire's in their eyes and their words are really clear\r",
            "showAt": 45.28300857543945,
            "hideAt": 48.533416748046878
        },
        {
            "lyric": "So beat it, just beat it\r",
            "showAt": 48.533416748046878,
            "hideAt": 52.68278884887695
        },
        {
            "lyric": "You better run, you better do what you can\r",
            "showAt": 52.68278884887695,
            "hideAt": 55.767391204833987
        },
        {
            "lyric": "Don't wanna see no blood, don't be a macho man\r",
            "showAt": 55.767391204833987,
            "hideAt": 59.30051803588867
        },
        {
            "lyric": "You wanna be tough, better do what you can\r",
            "showAt": 59.30051803588867,
            "hideAt": 62.367881774902347
        },
        {
            "lyric": "So beat it, but you wanna be bad\r",
            "showAt": 62.367881774902347,
            "hideAt": 66.01402282714844
        },
        {
            "lyric": "Just beat it, beat it",
            "showAt": 66.01402282714844,
            "hideAt": 69.70973205566406
        },
        {
            "lyric": "No one wants to be defeated\r",
            "showAt": 69.70973205566406,
            "hideAt": 73.09954071044922
        },
        {
            "lyric": "Showin' how funky and strong is your fight\r",
            "showAt": 73.09954071044922,
            "hideAt": 76.51563262939453
        },
        {
            "lyric": "It doesn't matter who's wrong or right\r",
            "showAt": 76.51563262939453,
            "hideAt": 79.86174774169922
        },
        {
            "lyric": "Just beat it\r",
            "showAt": 79.86174774169922,
            "hideAt": 81.7595443725586
        },
        {
            "lyric": "Just beat it\r",
            "showAt": 81.7595443725586,
            "hideAt": 83.32439422607422
        },
        {
            "lyric": "Just beat it\r",
            "showAt": 83.32439422607422,
            "hideAt": 85.15560150146485
        },
        {
            "lyric": "Just beat it\r",
            "showAt": 85.15560150146485,
            "hideAt": 87.56946563720703
        },
        {
            "lyric": "They're out to get you, better leave while you can\r",
            "showAt": 87.56946563720703,
            "hideAt": 90.69699096679688
        },
        {
            "lyric": "Don't wanna be a boy, you wanna be a man\r",
            "showAt": 90.69699096679688,
            "hideAt": 94.02957153320313
        },
        {
            "lyric": "You wanna stay alive, better do what you can\r",
            "showAt": 94.02957153320313,
            "hideAt": 97.24584197998047
        },
        {
            "lyric": "So beat it, just beat it\r",
            "showAt": 97.24584197998047,
            "hideAt": 101.410888671875
        },
        {
            "lyric": "You have to show them that you're really not scared\r",
            "showAt": 101.410888671875,
            "hideAt": 104.52810668945313
        },
        {
            "lyric": "You're playin' with your life, this ain't no truth or dare\r",
            "showAt": 104.52810668945313,
            "hideAt": 107.97721099853516
        },
        {
            "lyric": "They'll kick you, then they'll beat you\r",
            "showAt": 107.97721099853516,
            "hideAt": 109.3291015625
        },
        {
            "lyric": "Then they'll tell you it's fair\r",
            "showAt": 109.3291015625,
            "hideAt": 111.12701416015625
        },
        {
            "lyric": "So beat it, but you wanna be bad\r",
            "showAt": 111.12701416015625,
            "hideAt": 114.75613403320313
        },
        {
            "lyric": "Just beat it, beat it",
            "showAt": 114.75613403320313,
            "hideAt": 118.43519592285156
        },
        {
            "lyric": "No one wants to be defeated\r",
            "showAt": 118.43519592285156,
            "hideAt": 121.84172821044922
        },
        {
            "lyric": "Showin' how funky and strong is your fight\r",
            "showAt": 121.84172821044922,
            "hideAt": 125.3077621459961
        },
        {
            "lyric": "It doesn't matter who's wrong or right\r",
            "showAt": 125.3077621459961,
            "hideAt": 128.72047424316407
        },
        {
            "lyric": "Just beat it, beat it",
            "showAt": 128.72047424316407,
            "hideAt": 132.36624145507813
        },
        {
            "lyric": "No one wants to be defeated\r",
            "showAt": 132.36624145507813,
            "hideAt": 135.73951721191407
        },
        {
            "lyric": "Showin' how funky and strong is your fight\r",
            "showAt": 135.73951721191407,
            "hideAt": 139.2887725830078
        },
        {
            "lyric": "It doesn't matter who's wrong or right\r",
            "showAt": 139.2887725830078,
            "hideAt": 142.66818237304688
        },
        {
            "lyric": "Just beat it",
            "showAt": 142.66818237304688,
            "hideAt": 146.2140655517578
        },
        {
            "lyric": "♪",
            "showAt": 146.2140655517578,
            "hideAt": 198.7359619140625
        },
        {
            "lyric": "Beat it, beat it",
            "showAt": 198.7359619140625,
            "hideAt": 201.93572998046876
        },
        {
            "lyric": "No one wants to be defeated\r",
            "showAt": 201.93572998046876,
            "hideAt": 205.34866333007813
        },
        {
            "lyric": "Showin' how funky and strong is your fight\r",
            "showAt": 205.34866333007813,
            "hideAt": 208.89794921875
        },
        {
            "lyric": "It doesn't matter who's wrong or right\r",
            "showAt": 208.89794921875,
            "hideAt": 212.26071166992188
        },
        {
            "lyric": "Just beat it, beat it",
            "showAt": 212.26071166992188,
            "hideAt": 216.02301025390626
        },
        {
            "lyric": "No one wants to be defeated",
            "showAt": 216.02301025390626,
            "hideAt": 219.32986450195313
        },
        {
            "lyric": "Showin' how funky and strong is your fight\r",
            "showAt": 219.32986450195313,
            "hideAt": 222.9456329345703
        },
        {
            "lyric": "It doesn't matter who's wrong or right\r",
            "showAt": 222.9456329345703,
            "hideAt": 226.20851135253907
        },
        {
            "lyric": "Just beat it, beat it",
            "showAt": 226.20851135253907,
            "hideAt": 229.82098388671876
        },
        {
            "lyric": "No one wants to be defeated",
            "showAt": 229.82098388671876,
            "hideAt": 233.46060180664063
        },
        {
            "lyric": "Showin' how funky and strong is your fight\r",
            "showAt": 233.46060180664063,
            "hideAt": 236.74374389648438
        },
        {
            "lyric": "It doesn't matter who's wrong or right\r",
            "showAt": 236.74374389648438,
            "hideAt": 240.20639038085938
        },
        {
            "lyric": "Just beat it, beat it",
            "showAt": 240.20639038085938,
            "hideAt": 243.80221557617188
        },
        {
            "lyric": "No one wants to be defeated\r",
            "showAt": 243.80221557617188,
            "hideAt": 247.15869140625
        },
        {
            "lyric": "Showin' how funky and strong is your fight\r",
            "showAt": 247.15869140625,
            "hideAt": 250.64132690429688
        },
        {
            "lyric": "It doesn't matter who's wrong or right\r",
            "showAt": 250.64132690429688,
            "hideAt": 255.64132690429688
        }
    ]
}