{
    "lyrics": [
        {
            "lyric": "♪",
            "showAt": 0.0,
            "hideAt": 10.39963436126709
        },
        {
            "lyric": "Ey",
            "showAt": 10.39963436126709,
            "hideAt": 10.882962226867676
        },
        {
            "lyric": "Tití me preguntó",
            "showAt": 10.882962226867676,
            "hideAt": 11.999619483947754
        },
        {
            "lyric": "Si tengo muchas novia'",
            "showAt": 11.999619483947754,
            "hideAt": 14.616643905639649
        },
        {
            "lyric": "Muchas novia'",
            "showAt": 14.616643905639649,
            "hideAt": 15.58352279663086
        },
        {
            "lyric": "Hoy tengo a una, mañana otra",
            "showAt": 15.58352279663086,
            "hideAt": 18.366559982299806
        },
        {
            "lyric": "Ey, pero no hay boda",
            "showAt": 18.366559982299806,
            "hideAt": 19.966341018676759
        },
        {
            "lyric": "Tití me preguntó",
            "showAt": 19.966341018676759,
            "hideAt": 21.132898330688478
        },
        {
            "lyric": "Si tengo muchas novia', je",
            "showAt": 21.132898330688478,
            "hideAt": 23.86615753173828
        },
        {
            "lyric": "Muchas novia'",
            "showAt": 23.86615753173828,
            "hideAt": 24.89993667602539
        },
        {
            "lyric": "Hoy tengo una, mañana otra",
            "showAt": 24.89993667602539,
            "hideAt": 28.04969024658203
        },
        {
            "lyric": "Me la' vo'a llevar a to'a",
            "showAt": 28.04969024658203,
            "hideAt": 29.599822998046876
        },
        {
            "lyric": "Pa' un VIP, un VIP, ey",
            "showAt": 29.599822998046876,
            "hideAt": 32.53282928466797
        },
        {
            "lyric": "Saluden a Tití",
            "showAt": 32.53282928466797,
            "hideAt": 33.63301467895508
        },
        {
            "lyric": "Vamo' a tirarno' un selfie, Say \"Cheese\", ey",
            "showAt": 33.63301467895508,
            "hideAt": 36.49991226196289
        },
        {
            "lyric": "Que sonrían las que ya les metí",
            "showAt": 36.49991226196289,
            "hideAt": 38.0333366394043
        },
        {
            "lyric": "En un VIP, un VIP, ey",
            "showAt": 38.0333366394043,
            "hideAt": 41.20025634765625
        },
        {
            "lyric": "Saluden a Tití",
            "showAt": 41.20025634765625,
            "hideAt": 42.266910552978519
        },
        {
            "lyric": "Vamo' a tirarno' un selfie, Say \"Cheese\"",
            "showAt": 42.266910552978519,
            "hideAt": 44.8166389465332
        },
        {
            "lyric": "Que sonrían las que ya se olvidaron de mí",
            "showAt": 44.8166389465332,
            "hideAt": 46.58333969116211
        },
        {
            "lyric": "Me gustan mucho las Gabriela",
            "showAt": 46.58333969116211,
            "hideAt": 48.11673355102539
        },
        {
            "lyric": "Las Patricia, las Nicolle, las Sofía",
            "showAt": 48.11673355102539,
            "hideAt": 50.967288970947269
        },
        {
            "lyric": "Mi primera novia en kinder, María",
            "showAt": 50.967288970947269,
            "hideAt": 53.36748504638672
        },
        {
            "lyric": "Y mi primer amor se llamaba Thalía",
            "showAt": 53.36748504638672,
            "hideAt": 55.28432083129883
        },
        {
            "lyric": "Tengo una colombiana que me escribe to' los día'",
            "showAt": 55.28432083129883,
            "hideAt": 57.76783752441406
        },
        {
            "lyric": "Y una mexicana que ni yo sabía",
            "showAt": 57.76783752441406,
            "hideAt": 59.934268951416019
        },
        {
            "lyric": "Otra en San Antonio que me quiere todavía",
            "showAt": 59.934268951416019,
            "hideAt": 62.00114059448242
        },
        {
            "lyric": "Y las de PR que todita' son mía'",
            "showAt": 62.00114059448242,
            "hideAt": 64.20156860351563
        },
        {
            "lyric": "Una dominicana que es uva bombón",
            "showAt": 64.20156860351563,
            "hideAt": 66.6845474243164
        },
        {
            "lyric": "Uva, uva bombón",
            "showAt": 66.6845474243164,
            "hideAt": 68.45075225830078
        },
        {
            "lyric": "La de Barcelona que vino en avión",
            "showAt": 68.45075225830078,
            "hideAt": 70.95060729980469
        },
        {
            "lyric": "Y dice que mi bicho está cabrón",
            "showAt": 70.95060729980469,
            "hideAt": 72.61705780029297
        },
        {
            "lyric": "Yo dejo que jueguen",
            "showAt": 72.61705780029297,
            "hideAt": 74.08333587646485
        },
        {
            "lyric": "Con mi corazón",
            "showAt": 74.08333587646485,
            "hideAt": 75.06671142578125
        },
        {
            "lyric": "Quisiera mudarme con todas pa' una mansión",
            "showAt": 75.06671142578125,
            "hideAt": 77.19972229003906
        },
        {
            "lyric": "El día que me case te envío la invitación",
            "showAt": 77.19972229003906,
            "hideAt": 79.13286590576172
        },
        {
            "lyric": "Muchacho, deja eso, ey",
            "showAt": 79.13286590576172,
            "hideAt": 81.1823501586914
        },
        {
            "lyric": "Tití me preguntó",
            "showAt": 81.1823501586914,
            "hideAt": 82.29902648925781
        },
        {
            "lyric": "Si tengo muchas novia', muchas novia'",
            "showAt": 82.29902648925781,
            "hideAt": 85.9152603149414
        },
        {
            "lyric": "Hoy tengo una, mañana otra",
            "showAt": 85.9152603149414,
            "hideAt": 88.51486206054688
        },
        {
            "lyric": "Ey, pero no hay boda",
            "showAt": 88.51486206054688,
            "hideAt": 89.99783325195313
        },
        {
            "lyric": "Tití me preguntó",
            "showAt": 89.99783325195313,
            "hideAt": 91.08122253417969
        },
        {
            "lyric": "Si tengo muchas novia'",
            "showAt": 91.08122253417969,
            "hideAt": 92.78102111816406
        },
        {
            "lyric": "Ey, ey, muchas novia'",
            "showAt": 92.78102111816406,
            "hideAt": 94.51396942138672
        },
        {
            "lyric": "Hoy tengo una, mañana otra (mañana otra) (rrra)",
            "showAt": 94.51396942138672,
            "hideAt": 98.61326599121094
        },
        {
            "lyric": "Tití me preguntó-tó-tó-tó-tó-tó-tó",
            "showAt": 98.61326599121094,
            "hideAt": 102.92945861816406
        },
        {
            "lyric": "Tití me preguntó-tó-tó-tó-tó-tó-tó (qué pámpara)",
            "showAt": 102.92945861816406,
            "hideAt": 107.36221313476563
        },
        {
            "lyric": "Tití me preguntó-tó-tó-tó-tó-tó-tó",
            "showAt": 107.36221313476563,
            "hideAt": 111.44471740722656
        },
        {
            "lyric": "Tití me preguntó-tó-tó-tó",
            "showAt": 111.44471740722656,
            "hideAt": 114.22809600830078
        },
        {
            "lyric": "(Pero ven acá, muchacho, ¿Y para qué tú quiere' tanta' novia'?)",
            "showAt": 114.22809600830078,
            "hideAt": 116.92762756347656
        },
        {
            "lyric": "Me la' vo'a llevar a to'a",
            "showAt": 116.92762756347656,
            "hideAt": 118.1776351928711
        },
        {
            "lyric": "Pa' un VIP, un VIP, ey",
            "showAt": 118.1776351928711,
            "hideAt": 121.16059875488281
        },
        {
            "lyric": "Saluden a Tití",
            "showAt": 121.16059875488281,
            "hideAt": 122.27729034423828
        },
        {
            "lyric": "Vamo' a tirarno' un selfie, Say \"Cheese\", ey",
            "showAt": 122.27729034423828,
            "hideAt": 125.07695770263672
        },
        {
            "lyric": "Que sonrían las que ya les metí",
            "showAt": 125.07695770263672,
            "hideAt": 126.62666320800781
        },
        {
            "lyric": "En un VIP, un VIP, ey",
            "showAt": 126.62666320800781,
            "hideAt": 129.75953674316407
        },
        {
            "lyric": "Saluden a Tití",
            "showAt": 129.75953674316407,
            "hideAt": 130.87603759765626
        },
        {
            "lyric": "Vamo' a tirarno' un selfie, Say \"Cheese\"",
            "showAt": 130.87603759765626,
            "hideAt": 133.29251098632813
        },
        {
            "lyric": "Que sonrían las que ya se olvidaron de mí",
            "showAt": 133.29251098632813,
            "hideAt": 136.9920654296875
        },
        {
            "lyric": "Oye, muchacho 'el diablo, azaroso",
            "showAt": 136.9920654296875,
            "hideAt": 138.67506408691407
        },
        {
            "lyric": "Suelta ese mal vivir que tú tiene' en la calle",
            "showAt": 138.67506408691407,
            "hideAt": 140.95823669433595
        },
        {
            "lyric": "Búscate una mujer seria pa' ti",
            "showAt": 140.95823669433595,
            "hideAt": 142.941162109375
        },
        {
            "lyric": "Muchacho 'el diablo, coño",
            "showAt": 142.941162109375,
            "hideAt": 145.1243896484375
        },
        {
            "lyric": "",
            "showAt": 145.1243896484375,
            "hideAt": 145.97425842285157
        },
        {
            "lyric": "Yo quisiera enamorarme",
            "showAt": 145.97425842285157,
            "hideAt": 149.3404998779297
        },
        {
            "lyric": "Pero no puedo",
            "showAt": 149.3404998779297,
            "hideAt": 151.67343139648438
        },
        {
            "lyric": "Pero no puedo, eh, eh",
            "showAt": 151.67343139648438,
            "hideAt": 155.0395965576172
        },
        {
            "lyric": "Yo quisiera enamorarme",
            "showAt": 155.0395965576172,
            "hideAt": 158.68922424316407
        },
        {
            "lyric": "Pero no puedo",
            "showAt": 158.68922424316407,
            "hideAt": 160.97225952148438
        },
        {
            "lyric": "Pero no puedo",
            "showAt": 160.97225952148438,
            "hideAt": 163.10520935058595
        },
        {
            "lyric": "Sorry, yo no confío, yo no confío",
            "showAt": 163.10520935058595,
            "hideAt": 166.0218963623047
        },
        {
            "lyric": "Nah, ni en mí mismo confío",
            "showAt": 166.0218963623047,
            "hideAt": 168.37118530273438
        },
        {
            "lyric": "Si quieres quedarte hoy que hace frío",
            "showAt": 168.37118530273438,
            "hideAt": 170.35427856445313
        },
        {
            "lyric": "Y mañana te va', nah",
            "showAt": 170.35427856445313,
            "hideAt": 172.3702850341797
        },
        {
            "lyric": "Muchas quieren mi baby gravy",
            "showAt": 172.3702850341797,
            "hideAt": 174.20327758789063
        },
        {
            "lyric": "Quieren tener mi primogénito, ey",
            "showAt": 174.20327758789063,
            "hideAt": 176.28656005859376
        },
        {
            "lyric": "Y llevarse el crédito",
            "showAt": 176.28656005859376,
            "hideAt": 177.62005615234376
        },
        {
            "lyric": "Ya me aburrí",
            "showAt": 177.62005615234376,
            "hideAt": 178.35317993164063
        },
        {
            "lyric": "Hoy quiero un totito inédito, je",
            "showAt": 178.35317993164063,
            "hideAt": 180.10296630859376
        },
        {
            "lyric": "Uno nuevo, uno nuevo, uno nuevo, uno nuevo (ey)",
            "showAt": 180.10296630859376,
            "hideAt": 182.81924438476563
        },
        {
            "lyric": "Hazle caso a tu amiga, ella tiene razón",
            "showAt": 182.81924438476563,
            "hideAt": 186.38555908203126
        },
        {
            "lyric": "Yo vo'a romperte el corazón",
            "showAt": 186.38555908203126,
            "hideAt": 188.93521118164063
        },
        {
            "lyric": "Vo'a romperte el corazón",
            "showAt": 188.93521118164063,
            "hideAt": 192.4680633544922
        },
        {
            "lyric": "Ey, no te enamores de mí",
            "showAt": 192.4680633544922,
            "hideAt": 194.46783447265626
        },
        {
            "lyric": "No te enamores de mí",
            "showAt": 194.46783447265626,
            "hideAt": 197.01734924316407
        },
        {
            "lyric": "Sorry, yo soy así, ey",
            "showAt": 197.01734924316407,
            "hideAt": 199.15060424804688
        },
        {
            "lyric": "No sé por qué soy así",
            "showAt": 199.15060424804688,
            "hideAt": 201.71688842773438
        },
        {
            "lyric": "Hazle caso a tu amiga, ella tiene razón",
            "showAt": 201.71688842773438,
            "hideAt": 204.99981689453126
        },
        {
            "lyric": "Yo vo'a romperte el corazón",
            "showAt": 204.99981689453126,
            "hideAt": 207.41607666015626
        },
        {
            "lyric": "Vo'a romperte el corazón",
            "showAt": 207.41607666015626,
            "hideAt": 211.31564331054688
        },
        {
            "lyric": "No te enamores de mí",
            "showAt": 211.31564331054688,
            "hideAt": 213.09864807128907
        },
        {
            "lyric": "No te enamores de mí",
            "showAt": 213.09864807128907,
            "hideAt": 215.81504821777345
        },
        {
            "lyric": "Sorry, yo soy así",
            "showAt": 215.81504821777345,
            "hideAt": 217.76478576660157
        },
        {
            "lyric": "Ya no quiero ser así, no",
            "showAt": 217.76478576660157,
            "hideAt": 220.5311279296875
        },
        {
            "lyric": "♪",
            "showAt": 220.5311279296875,
            "hideAt": 239.76126098632813
        },
        {
            "lyric": "",
            "showAt": 239.76126098632813,
            "hideAt": 244.76126098632813
        }
    ]
}