{
    "lyrics": [
        {
            "lyric": "♪",
            "showAt": 1.7860108613967896,
            "hideAt": 8.16917610168457
        },
        {
            "lyric": "Yeah",
            "showAt": 8.16917610168457,
            "hideAt": 9.5960054397583
        },
        {
            "lyric": "With a boy like that it's serious",
            "showAt": 9.5960054397583,
            "hideAt": 16.616811752319337
        },
        {
            "lyric": "There is a boy who is so wonderful",
            "showAt": 16.616811752319337,
            "hideAt": 24.35324478149414
        },
        {
            "lyric": "That girls who see him cannot find back home",
            "showAt": 24.35324478149414,
            "hideAt": 31.689495086669923
        },
        {
            "lyric": "And the gigolos run like spiders when he comes",
            "showAt": 31.689495086669923,
            "hideAt": 40.438907623291019
        },
        {
            "lyric": "'Cause he's Eros and he's Apollo",
            "showAt": 40.438907623291019,
            "hideAt": 47.78642272949219
        },
        {
            "lyric": "Girls",
            "showAt": 47.78642272949219,
            "hideAt": 49.11146926879883
        },
        {
            "lyric": "With a boy like that it's serious",
            "showAt": 49.11146926879883,
            "hideAt": 55.64960479736328
        },
        {
            "lyric": "Señoritas",
            "showAt": 55.64960479736328,
            "hideAt": 60.37950897216797
        },
        {
            "lyric": "Don't follow him",
            "showAt": 60.37950897216797,
            "hideAt": 63.69514846801758
        },
        {
            "lyric": "Soon, he will eat your hearts like cereals",
            "showAt": 63.69514846801758,
            "hideAt": 71.62433624267578
        },
        {
            "lyric": "Sweet Lolitas",
            "showAt": 71.62433624267578,
            "hideAt": 76.18392181396485
        },
        {
            "lyric": "Don't go, you're still young",
            "showAt": 76.18392181396485,
            "hideAt": 80.2099609375
        },
        {
            "lyric": "But every night they fall like dominoes",
            "showAt": 80.2099609375,
            "hideAt": 88.3065185546875
        },
        {
            "lyric": "How he does it?, only heaven knows",
            "showAt": 88.3065185546875,
            "hideAt": 94.97628784179688
        },
        {
            "lyric": "All the other men turn gay wherever he goes",
            "showAt": 94.97628784179688,
            "hideAt": 100.9896011352539
        },
        {
            "lyric": "Wow!",
            "showAt": 100.9896011352539,
            "hideAt": 103.45999908447266
        },
        {
            "lyric": "Girls",
            "showAt": 103.45999908447266,
            "hideAt": 104.92359161376953
        },
        {
            "lyric": "With a boy like that it's serious",
            "showAt": 104.92359161376953,
            "hideAt": 111.1397705078125
        },
        {
            "lyric": "Señoritas",
            "showAt": 111.1397705078125,
            "hideAt": 115.94784545898438
        },
        {
            "lyric": "Don't follow him",
            "showAt": 115.94784545898438,
            "hideAt": 119.20857238769531
        },
        {
            "lyric": "Soon, he will eat your hearts like cereals",
            "showAt": 119.20857238769531,
            "hideAt": 127.2088394165039
        },
        {
            "lyric": "Sweet Lolitas",
            "showAt": 127.2088394165039,
            "hideAt": 131.82261657714845
        },
        {
            "lyric": "Don't go, you're still young",
            "showAt": 131.82261657714845,
            "hideAt": 135.01123046875
        },
        {
            "lyric": "♪",
            "showAt": 135.01123046875,
            "hideAt": 152.9365234375
        },
        {
            "lyric": "Yeah",
            "showAt": 152.9365234375,
            "hideAt": 154.45013427734376
        },
        {
            "lyric": "With a boy like that it's serious",
            "showAt": 154.45013427734376,
            "hideAt": 160.8318328857422
        },
        {
            "lyric": "Señoritas",
            "showAt": 160.8318328857422,
            "hideAt": 165.62525939941407
        },
        {
            "lyric": "Don't go",
            "showAt": 165.62525939941407,
            "hideAt": 166.92428588867188
        },
        {
            "lyric": "Please, don't go",
            "showAt": 166.92428588867188,
            "hideAt": 168.83306884765626
        },
        {
            "lyric": "Soon, he will eat your hearts like cereals",
            "showAt": 168.83306884765626,
            "hideAt": 176.75172424316407
        },
        {
            "lyric": "Sweet Lolitas",
            "showAt": 176.75172424316407,
            "hideAt": 181.37220764160157
        },
        {
            "lyric": "Don't go, you're still young",
            "showAt": 181.37220764160157,
            "hideAt": 184.61398315429688
        },
        {
            "lyric": "♪",
            "showAt": 184.61398315429688,
            "hideAt": 192.61399841308595
        },
        {
            "lyric": "Sweet Lolitas",
            "showAt": 192.61399841308595,
            "hideAt": 197.11399841308595
        },
        {
            "lyric": "Don't go, you're still young",
            "showAt": 197.11399841308595,
            "hideAt": 200.0
        }
    ]
}